toggl_import_core/__init__.py
toggl_import_core/config.py
toggl_import_core/exceptions.py
toggl_import_core/time_entry.py
toggl_import_core/toggl_import.py
toggl_import_core/toggl_integrator.py
toggl_import_core-0.1.1.dist-info/METADATA
toggl_import_core-0.1.1.dist-info/WHEEL
toggl_import_core-0.1.1.dist-info/top_level.txt
toggl_import_core-0.1.1.dist-info/RECORD
