Metadata-Version: 2.1
Name: toggl-import-core
Version: 0.1.1
Summary: Core package for the Toggl import tool
Home-page: UNKNOWN
Author: Eduardo Canellas
Author-email: eduardocanellas@id.uff.br
License: UNKNOWN
Platform: UNKNOWN
Classifier: Programming Language :: Python :: 3
Classifier: License :: OSI Approved :: MIT License
Classifier: Operating System :: OS Independent
Requires-Python: >=3.6
